AUTHORS
LICENSE
MANIFEST.in
README.rst
TODO.md
setup.py
job_advert_manager.egg-info/PKG-INFO
job_advert_manager.egg-info/SOURCES.txt
job_advert_manager.egg-info/dependency_links.txt
job_advert_manager.egg-info/entry_points.txt
job_advert_manager.egg-info/top_level.txt
jobmanager/__init__.py
jobmanager/add_and_edit_container.py
jobmanager/category_list.py
jobmanager/job_advert_manager.py
jobmanager/job_adverts_model.py
jobmanager/job_adverts_view.py
jobmanager/search_container.py
jobmanager/stats_container.py